altplotlib/__init__.py
altplotlib/_base.py
altplotlib/data.py
altplotlib/themes.py
altplotlib-0.0.3.dist-info/AUTHORS.rst
altplotlib-0.0.3.dist-info/LICENSE.txt
altplotlib-0.0.3.dist-info/METADATA
altplotlib-0.0.3.dist-info/WHEEL
altplotlib-0.0.3.dist-info/top_level.txt
altplotlib-0.0.3.dist-info/RECORD
