Metadata-Version: 2.1
Name: altplotlib
Version: 0.0.3
Summary: matplotlib style OO bindings for altair
Home-page: https://github.com/evanr70/altplotlib
Author: Evan Roberts
Author-email: evan.roberts@kellogg.ox.ac.uk
License: mit
Platform: any
Classifier: Development Status :: 4 - Beta
Classifier: Programming Language :: Python
Requires-Dist: numpy
Requires-Dist: matplotlib
Requires-Dist: altair
Requires-Dist: pandas
Provides-Extra: testing
Requires-Dist: pytest ; extra == 'testing'
Requires-Dist: pytest-cov ; extra == 'testing'
